{"remainingRequest":"/home/vps/ppf/node_modules/babel-loader/lib/index.js??ref--13-2!/home/vps/ppf/src/apps/admin/actions/setTransactions.js","dependencies":[{"path":"/home/vps/ppf/src/apps/admin/actions/setTransactions.js","mtime":1671127551241},{"path":"/home/vps/ppf/.babelrc","mtime":1671127885972},{"path":"/home/vps/ppf/node_modules/cache-loader/dist/cjs.js","mtime":1671127657171},{"path":"/home/vps/ppf/node_modules/babel-loader/lib/index.js","mtime":1671127654997}],"contextDependencies":[],"result":["'use strict';\n\nObject.defineProperty(exports, \"__esModule\", {\n    value: true\n});\n\nvar _types = require('../types/types');\n\nvar setTransactions = function setTransactions(payload) {\n    return {\n        type: _types.SET_TRANSACTIONS,\n        payload: payload\n    };\n};\n\nexports.default = setTransactions;\nsetTransactions.i = 'setTransactions';\nsetTransactions.i = 'setTransactions';",null]}