{"remainingRequest":"/home/vps/ppf/node_modules/css-loader/index.js??ref--12-2!/home/vps/ppf/node_modules/postcss-loader/lib/index.js??ref--12-3!/home/vps/ppf/src/apps/client/ui/components/OpenedOrder/OpenedOrder.css","dependencies":[{"path":"/home/vps/ppf/src/apps/client/ui/components/OpenedOrder/OpenedOrder.css","mtime":1671127665297},{"path":"/home/vps/ppf/src/css/mixins.css","mtime":1671127532449},{"path":"/home/vps/ppf/node_modules/cache-loader/dist/cjs.js","mtime":1671127657171},{"path":"/home/vps/ppf/node_modules/css-loader/index.js","mtime":1671127657915},{"path":"/home/vps/ppf/node_modules/postcss-loader/lib/index.js","mtime":1671127665267}],"contextDependencies":[],"result":["exports = module.exports = require(\"../../../../../../node_modules/css-loader/lib/css-base.js\")(false);\n// imports\nexports.i(require(\"-!../../../../../../node_modules/css-loader/index.js??ref--12-2!../../../../../../node_modules/postcss-loader/lib/index.js??ref--12-3!../../../../../css/colors.css\"), undefined);\n\n// module\nexports.push([module.id, \".OpenedOrder__root_2ruz3 {\\n    text-align: center;\\n    height: 66px;\\n    font-family: sans-serif;\\n    background: #1B2033;\\n    box-shadow: 0px -4px 5px rgba(0, 0, 0, 0.15);\\n    position: relative;\\n    z-index: 1;\\n    display: flex;\\n    justify-content: flex-end;\\n    transition: all .5s ease;\\n    z-index: 12;\\n}\\n\\n@media(max-width: 1024px){\\n\\n.OpenedOrder__root_2ruz3 {\\n    z-index: 10\\n}\\n}\\n\\n@media(max-width: 544px) {\\n\\n.OpenedOrder__root_2ruz3 {\\n    height: 56px\\n}\\n}\\n\\n@media(max-height: 544px) {\\n\\n.OpenedOrder__root_2ruz3 {\\n    height: 56px\\n}\\n}\\n\\n.OpenedOrder__rootContainer_3KrPO {\\n    width: calc(100% - 84px);\\n    position: relative;\\n    display: flex;\\n    justify-content: space-between;\\n    white-space: nowrap;\\n    padding-right: 36px;\\n    transition: all .5s ease;\\n    background: #1B2033;\\n}\\n\\n@media(max-width: 1024px) {\\n\\n.OpenedOrder__rootContainer_3KrPO {\\n    width: 100%;\\n    padding-right: 0;\\n    z-index: 1\\n}\\n}\\n\\n.OpenedOrder__footerOrderContainer_18R08 {\\n    display: flex;\\n    position: absolute;\\n    top: 0;\\n    width: calc(100vw - 84px);\\n    right: 0;\\n}\\n\\n@media(max-width: 1024px) {\\n\\n.OpenedOrder__footerOrderContainer_18R08 {\\n    width: 100vw\\n}\\n}\\n\\n.OpenedOrder__leftContainer_3ylxw {\\n    display: flex;\\n    font-size: 16px;\\n    line-height: 21px;\\n    letter-spacing: 0.01em;\\n    font-family: FuturaPT-Medium;\\n    align-items: center;\\n    margin-right: 70px;\\n    background: #1B2033;\\n    z-index: 1;\\n}\\n\\n.OpenedOrder__leftContainer_3ylxw .OpenedOrder__leftContainerItem_2NfHZ {\\n    display: flex;\\n    color: rgba(248, 248, 248, 0.75);\\n    padding: 0 36px;\\n    align-items: center;\\n    height: 100%;\\n    transition: all .3s ease;\\n    position: relative;\\n}\\n\\n.OpenedOrder__leftContainer_3ylxw .OpenedOrder__leftContainerItem_2NfHZ:last-child {\\n     color: #A6B1DC;\\n }\\n\\n.OpenedOrder__leftContainer_3ylxw .OpenedOrder__leftContainerItem_2NfHZ:not(:last-child){\\n     cursor: pointer;\\n}\\n\\n.OpenedOrder__leftContainer_3ylxw .OpenedOrder__leftContainerItem_2NfHZ:not(:last-child):hover {\\n     background: #22273A;\\n }\\n\\n.OpenedOrder__leftContainer_3ylxw .OpenedOrder__leftContainerItem_2NfHZ::after {\\n     content: '';\\n     position: absolute;\\n     width: 100%;\\n     height: 2px;\\n     top: 0;\\n     left: 0;\\n     right: 0;\\n     margin: auto;\\n     z-index: 1;\\n     transition: all .3s ease;\\n     opacity: 0;\\n     background-color: #4D6ADC;\\n     box-shadow: 0 0 5px 1px #4D6ADC;\\n }\\n\\n.OpenedOrder__leftContainer_3ylxw .OpenedOrder__itemValue_2eeqW {\\n    color: rgba(248, 248, 248, 0.5);\\n    margin-left: 8px;\\n}\\n\\n@media(max-width: 1440px) {\\n\\n.OpenedOrder__leftContainer_3ylxw {\\n    margin-right: 20px\\n}\\n\\n    .OpenedOrder__leftContainer_3ylxw .OpenedOrder__leftContainerItem_2NfHZ {\\n        padding: 0 18px;\\n}\\n\\n.OpenedOrder__leftContainer_3ylxw .OpenedOrder__leftContainerItem_2NfHZ:last-child {\\n     display: none;\\n }\\n}\\n\\n@media(max-width: 1024px) {\\n\\n.OpenedOrder__leftContainer_3ylxw {\\n    margin-right: 0;\\n    width: 100%\\n}\\n\\n    .OpenedOrder__leftContainer_3ylxw .OpenedOrder__leftContainerItem_2NfHZ {\\n        width: 50%;\\n        justify-content: center;\\n}\\n\\n.OpenedOrder__leftContainer_3ylxw .OpenedOrder__leftContainerItem_2NfHZ::after {\\n     bottom: 0;\\n     top: initial;\\n }\\n}\\n\\n@media(max-width: 1024px) {\\n    .OpenedOrder__leftContainer_3ylxw .OpenedOrder__leftContainerItem_2NfHZ {\\n        flex-direction: column;\\n}\\n\\n    .OpenedOrder__leftContainer_3ylxw .OpenedOrder__leftContainerItem_2NfHZ .OpenedOrder__itemValue_2eeqW {\\n        margin-left: 0;\\n    }\\n}\\n\\n.OpenedOrder__middleContainer_3Jpjg {\\n    display: flex;\\n    align-items: center;\\n}\\n\\n.OpenedOrder__middleContainer_3Jpjg .OpenedOrder__middleContainerButton_3a7nY {\\n    padding: 8px 18px;\\n    display: flex;\\n    align-items: center;\\n    font-family: FuturaPT-Medium;\\n    font-size: 16px;\\n    line-height: 21px;\\n    letter-spacing: 0.01em;\\n    color: #A6B1DC;\\n    margin-right: 2px;\\n    white-space: nowrap;\\n}\\n\\n.OpenedOrder__middleContainer_3Jpjg .OpenedOrder__buttonItem_9Ix2- {\\n    font-family: FuturaPT-Medium;\\n    font-size: 16px;\\n    line-height: 21px;\\n    letter-spacing: 0.01em;\\n    color: #F8F8F8;\\n    margin-left: 8px;\\n    white-space: nowrap;\\n}\\n\\n.OpenedOrder__middleContainer_3Jpjg .OpenedOrder__pu_1Ghjb {\\n    display: none;\\n}\\n\\n.OpenedOrder__middleContainer_3Jpjg .OpenedOrder__facilities_1V9B2 {\\n    background: rgba(166, 177, 220, 0.25);\\n}\\n\\n.OpenedOrder__middleContainer_3Jpjg .OpenedOrder__pledge_3oSsR {\\n    background: rgba(242, 201, 76, 0.25);\\n}\\n\\n.OpenedOrder__middleContainer_3Jpjg .OpenedOrder__free_1-jfy {\\n    background: rgba(39, 174, 96, 0.25);\\n}\\n\\n@media(max-width: 1024px) {\\n\\n.OpenedOrder__middleContainer_3Jpjg {\\n    position: fixed;\\n    width: 100%;\\n    bottom: 66px;\\n    display: flex;\\n    overflow: auto;\\n    background: #1B2033;\\n    z-index: 11\\n}\\n\\n\\n.OpenedOrder__middleContainer_3Jpjg::-webkit-scrollbar {\\n     width: 0;\\n     height: 0;\\n }\\n\\n    .OpenedOrder__middleContainer_3Jpjg .OpenedOrder__middleContainerButton_3a7nY {\\n        width: 33.333334%;\\n        margin-right: 0;\\n    }\\n\\n    .OpenedOrder__middleContainer_3Jpjg .OpenedOrder__pu_1Ghjb {\\n        display: flex;\\n        background: #161A2A;\\n        min-width: 137px;\\n}\\n\\n    .OpenedOrder__middleContainer_3Jpjg .OpenedOrder__pu_1Ghjb span {\\n        color: rgba(248, 248, 248, 0.5);\\n    }\\n\\n.OpenedOrder__middleContainer_3Jpjg .OpenedOrder__facilities_1V9B2 {\\n    background: rgb(58,64,86);\\n    min-width: 186px;\\n}\\n\\n.OpenedOrder__middleContainer_3Jpjg .OpenedOrder__pledge_3oSsR {\\n    background: rgb(77,70,50);\\n    min-width: 145px;\\n}\\n\\n.OpenedOrder__middleContainer_3Jpjg .OpenedOrder__free_1-jfy {\\n    background: rgb(30,63,55);\\n    min-width: 199px;\\n}\\n}\\n\\n@media(max-width: 544px) {\\n\\n.OpenedOrder__middleContainer_3Jpjg {\\n    bottom: 56px\\n}\\n\\n    .OpenedOrder__middleContainer_3Jpjg .OpenedOrder__middleContainerButton_3a7nY {\\n        font-size: 12px;\\n        line-height: 15px;\\n        padding: 4px 12px;\\n}\\n\\n    .OpenedOrder__middleContainer_3Jpjg .OpenedOrder__middleContainerButton_3a7nY span {\\n        font-size: 12px;\\n        line-height: 15px;\\n    }\\n\\n.OpenedOrder__middleContainer_3Jpjg .OpenedOrder__pu_1Ghjb {\\n    min-width: 102px;\\n}\\n\\n.OpenedOrder__middleContainer_3Jpjg .OpenedOrder__facilities_1V9B2 {\\n    min-width: 139px;\\n}\\n\\n.OpenedOrder__middleContainer_3Jpjg .OpenedOrder__pledge_3oSsR {\\n    min-width: 108px;\\n}\\n\\n.OpenedOrder__middleContainer_3Jpjg .OpenedOrder__free_1-jfy {\\n    min-width: 149px;\\n}\\n}\\n\\n@media(max-height: 544px) {\\n\\n.OpenedOrder__middleContainer_3Jpjg {\\n    bottom: 56px\\n}\\n\\n    .OpenedOrder__middleContainer_3Jpjg .OpenedOrder__middleContainerButton_3a7nY {\\n        font-size: 12px;\\n        line-height: 15px;\\n        padding: 4px 12px;\\n}\\n\\n    .OpenedOrder__middleContainer_3Jpjg .OpenedOrder__middleContainerButton_3a7nY span {\\n        font-size: 12px;\\n        line-height: 15px;\\n    }\\n\\n.OpenedOrder__middleContainer_3Jpjg .OpenedOrder__pu_1Ghjb {\\n    min-width: 102px;\\n}\\n\\n.OpenedOrder__middleContainer_3Jpjg .OpenedOrder__facilities_1V9B2 {\\n    min-width: 139px;\\n}\\n\\n.OpenedOrder__middleContainer_3Jpjg .OpenedOrder__pledge_3oSsR {\\n    min-width: 108px;\\n}\\n\\n.OpenedOrder__middleContainer_3Jpjg .OpenedOrder__free_1-jfy {\\n    min-width: 149px;\\n}\\n}\\n\\n.OpenedOrder__rightContainer_3xIFG {\\n    display: flex;\\n    align-items: center;\\n}\\n\\n.OpenedOrder__rightContainer_3xIFG .OpenedOrder__buttonContainer_2yFVd {\\n    width: 32px;\\n    height: 32px;\\n    display: flex;\\n    justify-content: center;\\n    align-items: center;\\n    cursor: pointer;\\n    transition: all .3s ease;\\n}\\n\\n.OpenedOrder__rightContainer_3xIFG .OpenedOrder__buttonContainer_2yFVd path {\\n    transition: all .3s ease;\\n}\\n\\n.OpenedOrder__rightContainer_3xIFG .OpenedOrder__buttonContainer_2yFVd:first-child {\\n     margin-right: 44px;\\n }\\n\\n.OpenedOrder__rightContainer_3xIFG .OpenedOrder__buttonContainer_2yFVd:hover {\\n     background: #161A2A;\\n}\\n\\n.OpenedOrder__rightContainer_3xIFG .OpenedOrder__buttonContainer_2yFVd:hover path {\\n    fill: #F8F8F8;\\n}\\n\\n.OpenedOrder__rightContainer_3xIFG .OpenedOrder__activeButton_35Ck2 {\\n    background: #161A2A;\\n}\\n\\n.OpenedOrder__rightContainer_3xIFG .OpenedOrder__activeButton_35Ck2 path {\\n    fill: #F8F8F8;\\n}\\n\\n@media(max-width: 1440px) {\\n.OpenedOrder__rightContainer_3xIFG .OpenedOrder__buttonContainer_2yFVd:first-child {\\n     margin-right: 20px;\\n }\\n}\\n\\n@media(max-width: 1120px) {\\n\\n.OpenedOrder__rightContainer_3xIFG {\\n    display: none\\n}\\n}\\n\\n@media(max-width: 1024px) {\\n\\n.OpenedOrder__rightContainer_3xIFG {\\n    display: none\\n}\\n}\\n\\n.OpenedOrder__footerOpenContainer_2X7rh {\\n    position: absolute;\\n    background: #1B2033;\\n    top: 65px;\\n    left: 0;\\n    display: flex;\\n    justify-content: flex-start;\\n    flex-direction: row;\\n    overflow: hidden;\\n    width: 999999px;\\n    transition: all .5s ease;\\n}\\n\\n@media(max-width: 1024px) {\\n\\n.OpenedOrder__footerOpenContainer_2X7rh {\\n    height: unset\\n}\\n}\\n\\n@media(max-width: 544px) {\\n\\n.OpenedOrder__footerOpenContainer_2X7rh {\\n    top: 56px\\n}\\n}\\n\\n@media(max-height: 544px) {\\n\\n.OpenedOrder__footerOpenContainer_2X7rh {\\n    top: 56px;\\n    overflow: hidden\\n}\\n}\\n\\n.OpenedOrder__openPositionSlide_3tq3M, .OpenedOrder__closePositionSlide_2ys3a {\\n    display: flex;\\n    flex-direction: column;\\n    overflow: auto;\\n    width: calc(100vw - 84px);\\n    height: calc(44vh + 1px);\\n    transition-delay: .5s;\\n}\\n\\n.OpenedOrder__openPositionSlide_3tq3M::-webkit-scrollbar, .OpenedOrder__closePositionSlide_2ys3a::-webkit-scrollbar {\\n     width: 7px;\\n     height: 7px;\\n }\\n\\n.OpenedOrder__openPositionSlide_3tq3M::-webkit-scrollbar-thumb, .OpenedOrder__closePositionSlide_2ys3a::-webkit-scrollbar-thumb {\\n     background: rgba(166, 177, 220, 0.5);\\n     border-radius: 10px;\\n }\\n\\n.OpenedOrder__openPositionSlide_3tq3M::-webkit-scrollbar-thumb:hover, .OpenedOrder__closePositionSlide_2ys3a::-webkit-scrollbar-thumb:hover {\\n     background: rgb(133, 146, 201);\\n }\\n\\n@media(max-width: 1024px) {\\n\\n.OpenedOrder__openPositionSlide_3tq3M, .OpenedOrder__closePositionSlide_2ys3a {\\n    align-items: flex-start;\\n    overflow: auto;\\n    height: calc(100vh - 252px);\\n    width: 100vw\\n}\\n\\n.OpenedOrder__openPositionSlide_3tq3M::-webkit-scrollbar, .OpenedOrder__closePositionSlide_2ys3a::-webkit-scrollbar {\\n     width: 2px;\\n     height: 2px;\\n }\\n}\\n\\n@media(max-width: 544px) {\\n\\n.OpenedOrder__openPositionSlide_3tq3M, .OpenedOrder__closePositionSlide_2ys3a {\\n    height: calc(100vh - 191px)\\n}\\n}\\n\\n@media(max-height: 544px) {\\n\\n.OpenedOrder__openPositionSlide_3tq3M, .OpenedOrder__closePositionSlide_2ys3a {\\n    height: calc(100vh - 191px)\\n}\\n}\\n\\n.OpenedOrder__footerContentVisible_16bvy {\\n    -webkit-transform: translateY(-44vh);\\n            transform: translateY(-44vh);\\n}\\n\\n@media(max-width: 1024px) {\\n\\n.OpenedOrder__footerContentVisible_16bvy {\\n    -webkit-transform: translateY(calc(-100vh + 150px));\\n            transform: translateY(calc(-100vh + 150px))\\n}\\n}\\n\\n@media(max-width: 544px) {\\n\\n.OpenedOrder__footerContentVisible_16bvy {\\n    -webkit-transform: translateY(calc(-100vh + 112px));\\n            transform: translateY(calc(-100vh + 112px))\\n}\\n}\\n\\n@media(max-height: 544px) {\\n\\n.OpenedOrder__footerContentVisible_16bvy {\\n    -webkit-transform: translateY(calc(-100vh + 112px));\\n            transform: translateY(calc(-100vh + 112px))\\n}\\n}\\n\\n@media(min-width: 1024px) {\\n\\n.OpenedOrder__footerContentVisibleFullSize_1qnQ3 {\\n    -webkit-transform: translateY(calc(-100vh + 150px)) !important;\\n            transform: translateY(calc(-100vh + 150px)) !important;\\n    height: calc(100vh - 149px) !important\\n}\\n}\\n\\n@media(min-width: 1024px) {\\n\\n.OpenedOrder__footerRootContainerFullSize_c3Tm9 {\\n    -webkit-transform: translateY(calc(-100vh + 149px)) !important;\\n            transform: translateY(calc(-100vh + 149px)) !important\\n}\\n}\\n\\n.OpenedOrder__footerHeaderTable_1wtSJ {\\n    height: 48px;\\n    display: flex;\\n    font-family: FuturaPT-Medium;\\n    font-size: 14px;\\n    line-height: 18px;\\n    letter-spacing: 0.012em;\\n    color: rgba(166, 177, 220, 0.75);\\n    text-align: left;\\n    align-items: center;\\n    white-space: nowrap;\\n    justify-content: space-between;\\n    padding: 15px 0;\\n    position: -webkit-sticky;\\n    position: sticky;\\n    top: 0;\\n    background: rgb(34,39,59);\\n    z-index: 1;\\n    min-width: 1360px;\\n    width: 100%;\\n}\\n\\n@media(max-width: 1024px) {\\n\\n.OpenedOrder__footerHeaderTable_1wtSJ {\\n    width: -webkit-fit-content;\\n    width: -moz-fit-content;\\n    width: fit-content;\\n    position: -webkit-sticky;\\n    position: sticky;\\n    top: 0;\\n    z-index: 23;\\n    background: rgb(34,39,59)\\n}\\n}\\n\\n.OpenedOrder__footerRowsContainer_3ZCQf {\\n    display: flex;\\n    align-items: flex-start;\\n    flex-direction: column;\\n    min-width: 1360px;\\n    width: 100%;\\n}\\n\\n@media(max-width: 1024px) {\\n\\n.OpenedOrder__footerRowsContainer_3ZCQf {\\n    width: -webkit-fit-content;\\n    width: -moz-fit-content;\\n    width: fit-content\\n}\\n}\\n\\n.OpenedOrder__itemNum_1nv_- {\\n    min-width: 80px;\\n    text-align: center;\\n    justify-content: center;\\n}\\n\\n.OpenedOrder__itemCreateDate_2OWSW {\\n    min-width: 124px;\\n}\\n\\n.OpenedOrder__itemCloseDate_wnPSG {\\n    min-width: 124px;\\n}\\n\\n.OpenedOrder__itemAsset_DFGWc {\\n    min-width: 148px;\\n}\\n\\n.OpenedOrder__itemAsset_DFGWc .OpenedOrder__firstImg_2DEF0 {\\n    margin-right: 8px;\\n}\\n\\n.OpenedOrder__itemAsset_DFGWc .OpenedOrder__secondImg_2u4Ta {\\n    margin-left: 7px;\\n}\\n\\n.OpenedOrder__profitAndLoss_Nhcz4 {\\n    min-width: 106px;\\n}\\n\\n.OpenedOrder__itemAmount__G4yN {\\n    min-width: 106px;\\n}\\n\\n.OpenedOrder__itemPledge_1pv_n {\\n    min-width: 112px;\\n}\\n\\n.OpenedOrder__itemOpeningRate_2eKm4 {\\n    min-width: 149px;\\n}\\n\\n.OpenedOrder__itemClosingRate_3RBcW {\\n    min-width: 186px;\\n}\\n\\n.OpenedOrder__itemProfit_1p4wr {\\n    min-width: 117px;\\n}\\n\\n.OpenedOrder__itemCommission_2V0Rf {\\n    min-width: 70px;\\n}\\n\\n.OpenedOrder__itemClosingDate_1B0tj {\\n    min-width: 113px;\\n}\\n\\n.OpenedOrder__itemDiffRate_3J3Dz {\\n    margin-left: 9px;\\n}\\n\\n.OpenedOrder__footerItemTable_aJoQb {\\n    background: #1B2033;\\n    display: flex;\\n    border-bottom: 1px solid #333543;\\n    font-family: FuturaPT-Medium;\\n    font-size: 14px;\\n    line-height: 18px;\\n    letter-spacing: 0.012em;\\n    color: rgba(248, 248, 248, 0.75);\\n    text-align: left;\\n    justify-content: space-between;\\n    height: 57px;\\n    position: relative;\\n    transition: all .3s ease;\\n    width: inherit;\\n}\\n\\n.OpenedOrder__footerItemTable_aJoQb:hover {\\n     background: #22273A;\\n }\\n\\n.OpenedOrder__footerItemTable_aJoQb .OpenedOrder__itemAmount__G4yN, .OpenedOrder__footerItemTable_aJoQb .OpenedOrder__itemCommission_2V0Rf, .OpenedOrder__footerItemTable_aJoQb .OpenedOrder__itemPledge_1pv_n {\\n    color: #A6B1DC;\\n}\\n\\n.OpenedOrder__footerItemTable_aJoQb .OpenedOrder__itemClosingDate_1B0tj {\\n    justify-content: flex-end;\\n    padding-right: 16px;\\n    cursor: pointer;\\n}\\n\\n@media(max-width: 1024px) {\\n\\n.OpenedOrder__footerItemTable_aJoQb {\\n    width: 100%\\n}\\n}\\n\\n.OpenedOrder__footerItems_1FPde {\\n    display: flex;\\n    align-items: center;\\n\\n}\\n\\n.OpenedOrder__activePositionButton_h6nPq {\\n    background: #161A2A !important;\\n    color: #F8F8F8 !important;\\n    position: relative;\\n}\\n\\n.OpenedOrder__activePositionButton_h6nPq::after {\\n     opacity: 1 !important;\\n }\\n\\n.OpenedOrder__rootLeftColumn_1gi4I {\\n    position: fixed;\\n    z-index: 2;\\n    height: 0;\\n    width: 84px;\\n    left: 0;\\n    background: #1B2033;\\n    transition: all .5s ease;\\n    height: calc(44vh + 66px);\\n}\\n\\n@media(max-width: 1024px) {\\n\\n.OpenedOrder__rootLeftColumn_1gi4I {\\n    display: none\\n}\\n}\\n\\n.OpenedOrder__rootLeftColumnShow_3xgsJ {\\n    height: calc(44vh + 66px);\\n}\\n\\n.OpenedOrder__rootLeftFullSize_OSAa3 {\\n    height: calc(100vh - 82px) !important;\\n}\\n\\n@media(min-width: 1024px) {\\n\\n.OpenedOrder__rootLeftFullSize_OSAa3 {\\n    transition-delay: -5s\\n}\\n}\\n\\n.OpenedOrder__openPositionSlide_3tq3M .OpenedOrder__footerHeaderTable_1wtSJ .OpenedOrder__itemCommission_2V0Rf {\\n    min-width: 91px;\\n}\\n\\n.OpenedOrder__openPositionSlide_3tq3M .OpenedOrder__footerHeaderTable_1wtSJ .OpenedOrder__itemClosingDate_1B0tj {\\n    min-width: 205px;\\n}\\n\\n.OpenedOrder__openPositionSlide_3tq3M .OpenedOrder__footerRowsContainer_3ZCQf .OpenedOrder__itemCommission_2V0Rf {\\n    min-width: 128px;\\n}\\n\\n.OpenedOrder__openPositionSlide_3tq3M .OpenedOrder__footerRowsContainer_3ZCQf .OpenedOrder__itemClosingDate_1B0tj {\\n    font-family: FuturaPT-Medium;\\n    font-weight: 600;\\n    font-size: 16px;\\n    line-height: 21px;\\n    text-align: center;\\n    color: #A6B1DC;\\n    white-space: nowrap;\\n    width: auto;\\n    padding: 0 28px;\\n    min-width: 168px;\\n}\\n\\n.OpenedOrder__openPositionSlide_3tq3M .OpenedOrder__footerRowsContainer_3ZCQf .OpenedOrder__itemClosingDate_1B0tj:hover {\\n     background: #161A2A;\\n }\\n\\n.OpenedOrder__openPositionSlide_3tq3M .OpenedOrder__footerRowsContainer_3ZCQf .OpenedOrder__itemClosingDate_1B0tj .OpenedOrder__arrowIcons_1PScx {\\n    display: flex;\\n    height: 100%;\\n}\\n\\n.OpenedOrder__openPositionSlide_3tq3M .OpenedOrder__footerRowsContainer_3ZCQf .OpenedOrder__activeItemTable_iV1Y8 {\\n    background: #22273A;;\\n}\\n\\n@media(max-width: 1024px) {\\n    .OpenedOrder__openPositionSlide_3tq3M .OpenedOrder__footerRowsContainer_3ZCQf .OpenedOrder__itemCommission_2V0Rf {\\n        min-width: 91px;\\n    }\\n.OpenedOrder__openPositionSlide_3tq3M .OpenedOrder__footerHeaderTable_1wtSJ .OpenedOrder__itemClosingDate_1B0tj {\\n    min-width: 168px;\\n}\\n}\\n\\n.OpenedOrder__activeClosingData_2VT6O {\\n    background: #161A2A;\\n    cursor: default !important;\\n    min-width: 205px !important;\\n    padding: 0 28px 0 15px !important;\\n}\\n\\n.OpenedOrder__activeClosingData_2VT6O img {\\n    margin-left: 20px;\\n    cursor: pointer;\\n}\\n\\n.OpenedOrder__activeItemCommission_9blLM {\\n    min-width: 91px !important;\\n}\\n\\n@media(max-width: 1024px) {\\n\\n.OpenedOrder__activeItemCommission_9blLM {\\n    min-width: 54px !important\\n}\\n}\\n\\n.OpenedOrder__closeDealButton_vrgXd {\\n    height: 100%;\\n    display: flex;\\n    align-items: center;\\n}\\n\\n\\n.OpenedOrder__mobileOperations_3GB_x {\\n    display: flex;\\n}\\n\\n\\n.OpenedOrder__mobileOperations_3GB_x path {\\n    transition: all .3s ease;\\n}\\n\\n\\n@media(max-width: 1024px) {\\n\\n\\n.OpenedOrder__mobileOperations_3GB_x {\\n    display: flex;\\n    justify-content: center;\\n    align-items: center;\\n    flex-direction: column;\\n    width: 50%;\\n    background: #1B2033;\\n    cursor: pointer\\n}\\n}\\n\\n\\n@media(max-width: 544px) {\\n\\n\\n.OpenedOrder__mobileOperations_3GB_x {\\n    border-top: none\\n}\\n}\\n\\n.OpenedOrder__mobileAssetsButton_2wBiE {\\n    display: none;\\n}\\n\\n@media(max-width: 1024px) {\\n\\n.OpenedOrder__mobileAssetsButton_2wBiE {\\n    width: 100%;\\n    display: flex;\\n    justify-content: center;\\n    position: fixed;\\n    bottom: 0;\\n    height: 66px;\\n    background: #1B2033;\\n    z-index: 12\\n}\\n}\\n\\n@media(max-width: 544px) {\\n\\n.OpenedOrder__mobileAssetsButton_2wBiE {\\n    height: 56px\\n}\\n}\\n\\n@media(max-height: 544px) {\\n\\n.OpenedOrder__mobileAssetsButton_2wBiE {\\n    height: 56px\\n}\\n}\\n\\n.OpenedOrder__mobileOperationsTitle_3IQWt {\\n    font-family: FuturaPT-Medium;\\n    font-size: 12px;\\n    line-height: 15px;\\n    letter-spacing: 0.01em;\\n    color: #A6B1DC;\\n    margin-top: 5px;\\n}\\n\\n@media(max-width: 544px) {\\n\\n.OpenedOrder__mobileOperationsTitle_3IQWt {\\n    margin-top: 3px\\n}\\n}\\n\\n.OpenedOrder__mobileOperationsButton_2GVlE {\\n    display: none;\\n}\\n\\n@media(max-width: 1024px) {\\n\\n.OpenedOrder__mobileOperationsButton_2GVlE {\\n    display: flex;\\n    width: 100%;\\n    height: 100%;\\n    align-items: center;\\n    justify-content: center;\\n    flex-direction: column;\\n    position: relative\\n}\\n\\n.OpenedOrder__mobileOperationsButton_2GVlE::after {\\n     content: '';\\n     position: absolute;\\n     width: 100%;\\n     height: 2px;\\n     top: 0;\\n     left: 0;\\n     background: #4D6ADC;\\n     box-shadow: 0 0 5px 1px #4D6ADC;\\n     opacity: 0;\\n     transition: all .3s ease;\\n }\\n}\\n\\n@media(max-width: 544px) {\\n    .OpenedOrder__mobileOperationsButton_2GVlE svg {\\n        width: 15px;\\n        height: 18px;\\n    }\\n}\\n\\n.OpenedOrder__showMobileLeftContainer_2rZP9 {\\n    display: flex;\\n}\\n\\n@media(max-width: 1024px) {\\n\\n.OpenedOrder__showMobileLeftContainer_2rZP9 {\\n    width: 100%\\n}\\n}\\n\\n.OpenedOrder__mobileFooterButton_3gvWQ {\\n    display: flex;\\n    width: 100%;\\n    position: fixed;\\n    z-index: 1;\\n    bottom: 0;\\n    background: #1B2033;\\n    height: 66px;\\n}\\n\\n.OpenedOrder__middleContainerMobile_3_DCr{\\n    display: none;\\n}\\n\\n@media(max-width: 1024px) {\\n\\n.OpenedOrder__middleContainerMobile_3_DCr{\\n    display: flex!important\\n}\\n}\\n\\n@media(max-width: 1024px) {\\n\\n.OpenedOrder__middleContainerDesktop_2E0UF {\\n    display: none !important\\n}\\n}\\n\\n.OpenedOrder__mobileAssetsMiddleLine_3exAx {\\n    width: 1px;\\n    height: 100%;\\n    background: rgb(61,68,93);\\n}\\n\\n.OpenedOrder__mobileOperationsActive_2EnOF {\\n    background: #161A2A;\\n}\\n\\n.OpenedOrder__mobileOperationsActive_2EnOF::after {\\n     opacity: 1;\\n }\\n\\n.OpenedOrder__mobileOperationsActive_2EnOF path {\\n    fill: #F8F8F8\\n}\\n\\n.OpenedOrder__mobileOperationsActive_2EnOF .OpenedOrder__mobileOperationsTitle_3IQWt {\\n    color: #F8F8F8;\\n}\\n\\n.OpenedOrder__posValue_Hi8Xj {\\n    color: #27AE60 !important;\\n}\\n\\n.OpenedOrder__negValue_1o60f {\\n    color: rgba(235, 87, 87, 0.75) !important;\\n}\\n\\n.OpenedOrder__assetItemPair_33CIv {\\n    position: relative;\\n    width: 32px;\\n    height: 24px;\\n    margin-right: 16px;\\n}\\n\\n.OpenedOrder__imgUpper_15H0W {\\n    height: 16px;\\n    width: 21px;\\n    position: absolute;\\n    top: 0;\\n    left: 0;\\n    display: inline-block;\\n    background-color: white;\\n}\\n\\n.OpenedOrder__imgLower_1Poia {\\n    height: 16px;\\n    width: 21px;\\n    position: absolute;\\n    bottom: 0;\\n    right: 0;\\n    display: inline-block;\\n    background-color: white;\\n}\\n\\n.OpenedOrder__imgAlone_19B3L {\\n    height: 16px;\\n    width: 21px;\\n    position: absolute;\\n    top: 50%;\\n    left: 50%;\\n    -webkit-transform: translate(-50%, -50%);\\n            transform: translate(-50%, -50%);\\n    background-color: white;\\n}\\n\\n.OpenedOrder__positionsFullSize_1FTm2 {\\n    height: calc(100vh - 148px) !important;\\n    transition-delay: unset;\\n}\\n\\n.OpenedOrder__preloader_2h41y {\\n    margin-left: 20px;\\n    width: 26px;\\n    height: 26px;\\n}\\n\", \"\"]);\n\n// exports\nexports.locals = {\n\t\"deepBlue\": \"\" + require(\"-!../../../../../../node_modules/css-loader/index.js??ref--12-2!../../../../../../node_modules/postcss-loader/lib/index.js??ref--12-3!../../../../../css/colors.css\").locals[\"deepBlue\"] + \"\",\n\t\"lightBlue\": \"\" + require(\"-!../../../../../../node_modules/css-loader/index.js??ref--12-2!../../../../../../node_modules/postcss-loader/lib/index.js??ref--12-3!../../../../../css/colors.css\").locals[\"lightBlue\"] + \"\",\n\t\"redLight\": \"\" + require(\"-!../../../../../../node_modules/css-loader/index.js??ref--12-2!../../../../../../node_modules/postcss-loader/lib/index.js??ref--12-3!../../../../../css/colors.css\").locals[\"redLight\"] + \"\",\n\t\"whiteDingy\": \"\" + require(\"-!../../../../../../node_modules/css-loader/index.js??ref--12-2!../../../../../../node_modules/postcss-loader/lib/index.js??ref--12-3!../../../../../css/colors.css\").locals[\"whiteDingy\"] + \"\",\n\t\"lightBlueDingy\": \"\" + require(\"-!../../../../../../node_modules/css-loader/index.js??ref--12-2!../../../../../../node_modules/postcss-loader/lib/index.js??ref--12-3!../../../../../css/colors.css\").locals[\"lightBlueDingy\"] + \"\",\n\t\"root\": \"OpenedOrder__root_2ruz3\",\n\t\"rootContainer\": \"OpenedOrder__rootContainer_3KrPO\",\n\t\"footerOrderContainer\": \"OpenedOrder__footerOrderContainer_18R08\",\n\t\"leftContainer\": \"OpenedOrder__leftContainer_3ylxw\",\n\t\"leftContainerItem\": \"OpenedOrder__leftContainerItem_2NfHZ\",\n\t\"itemValue\": \"OpenedOrder__itemValue_2eeqW\",\n\t\"middleContainer\": \"OpenedOrder__middleContainer_3Jpjg\",\n\t\"middleContainerButton\": \"OpenedOrder__middleContainerButton_3a7nY\",\n\t\"buttonItem\": \"OpenedOrder__buttonItem_9Ix2-\",\n\t\"pu\": \"OpenedOrder__pu_1Ghjb\",\n\t\"facilities\": \"OpenedOrder__facilities_1V9B2\",\n\t\"pledge\": \"OpenedOrder__pledge_3oSsR\",\n\t\"free\": \"OpenedOrder__free_1-jfy\",\n\t\"rightContainer\": \"OpenedOrder__rightContainer_3xIFG\",\n\t\"buttonContainer\": \"OpenedOrder__buttonContainer_2yFVd\",\n\t\"activeButton\": \"OpenedOrder__activeButton_35Ck2\",\n\t\"footerOpenContainer\": \"OpenedOrder__footerOpenContainer_2X7rh\",\n\t\"openPositionSlide\": \"OpenedOrder__openPositionSlide_3tq3M\",\n\t\"closePositionSlide\": \"OpenedOrder__closePositionSlide_2ys3a\",\n\t\"footerContentVisible\": \"OpenedOrder__footerContentVisible_16bvy\",\n\t\"footerContentVisibleFullSize\": \"OpenedOrder__footerContentVisibleFullSize_1qnQ3\",\n\t\"footerRootContainerFullSize\": \"OpenedOrder__footerRootContainerFullSize_c3Tm9\",\n\t\"footerHeaderTable\": \"OpenedOrder__footerHeaderTable_1wtSJ\",\n\t\"footerRowsContainer\": \"OpenedOrder__footerRowsContainer_3ZCQf\",\n\t\"itemNum\": \"OpenedOrder__itemNum_1nv_-\",\n\t\"itemCreateDate\": \"OpenedOrder__itemCreateDate_2OWSW\",\n\t\"itemCloseDate\": \"OpenedOrder__itemCloseDate_wnPSG\",\n\t\"itemAsset\": \"OpenedOrder__itemAsset_DFGWc\",\n\t\"firstImg\": \"OpenedOrder__firstImg_2DEF0\",\n\t\"secondImg\": \"OpenedOrder__secondImg_2u4Ta\",\n\t\"profitAndLoss\": \"OpenedOrder__profitAndLoss_Nhcz4\",\n\t\"itemAmount\": \"OpenedOrder__itemAmount__G4yN\",\n\t\"itemPledge\": \"OpenedOrder__itemPledge_1pv_n\",\n\t\"itemOpeningRate\": \"OpenedOrder__itemOpeningRate_2eKm4\",\n\t\"itemClosingRate\": \"OpenedOrder__itemClosingRate_3RBcW\",\n\t\"itemProfit\": \"OpenedOrder__itemProfit_1p4wr\",\n\t\"itemCommission\": \"OpenedOrder__itemCommission_2V0Rf\",\n\t\"itemClosingDate\": \"OpenedOrder__itemClosingDate_1B0tj\",\n\t\"itemDiffRate\": \"OpenedOrder__itemDiffRate_3J3Dz\",\n\t\"footerItemTable\": \"OpenedOrder__footerItemTable_aJoQb\",\n\t\"footerItems\": \"OpenedOrder__footerItems_1FPde\",\n\t\"activePositionButton\": \"OpenedOrder__activePositionButton_h6nPq\",\n\t\"rootLeftColumn\": \"OpenedOrder__rootLeftColumn_1gi4I\",\n\t\"rootLeftColumnShow\": \"OpenedOrder__rootLeftColumnShow_3xgsJ\",\n\t\"rootLeftFullSize\": \"OpenedOrder__rootLeftFullSize_OSAa3\",\n\t\"arrowIcons\": \"OpenedOrder__arrowIcons_1PScx\",\n\t\"activeItemTable\": \"OpenedOrder__activeItemTable_iV1Y8\",\n\t\"activeClosingData\": \"OpenedOrder__activeClosingData_2VT6O\",\n\t\"activeItemCommission\": \"OpenedOrder__activeItemCommission_9blLM\",\n\t\"closeDealButton\": \"OpenedOrder__closeDealButton_vrgXd\",\n\t\"mobileOperations\": \"OpenedOrder__mobileOperations_3GB_x\",\n\t\"mobileAssetsButton\": \"OpenedOrder__mobileAssetsButton_2wBiE\",\n\t\"mobileOperationsTitle\": \"OpenedOrder__mobileOperationsTitle_3IQWt\",\n\t\"mobileOperationsButton\": \"OpenedOrder__mobileOperationsButton_2GVlE\",\n\t\"showMobileLeftContainer\": \"OpenedOrder__showMobileLeftContainer_2rZP9\",\n\t\"mobileFooterButton\": \"OpenedOrder__mobileFooterButton_3gvWQ\",\n\t\"middleContainerMobile\": \"OpenedOrder__middleContainerMobile_3_DCr\",\n\t\"middleContainerDesktop\": \"OpenedOrder__middleContainerDesktop_2E0UF\",\n\t\"mobileAssetsMiddleLine\": \"OpenedOrder__mobileAssetsMiddleLine_3exAx\",\n\t\"mobileOperationsActive\": \"OpenedOrder__mobileOperationsActive_2EnOF\",\n\t\"posValue\": \"OpenedOrder__posValue_Hi8Xj\",\n\t\"negValue\": \"OpenedOrder__negValue_1o60f\",\n\t\"assetItemPair\": \"OpenedOrder__assetItemPair_33CIv\",\n\t\"imgUpper\": \"OpenedOrder__imgUpper_15H0W\",\n\t\"imgLower\": \"OpenedOrder__imgLower_1Poia\",\n\t\"imgAlone\": \"OpenedOrder__imgAlone_19B3L\",\n\t\"positionsFullSize\": \"OpenedOrder__positionsFullSize_1FTm2\",\n\t\"preloader\": \"OpenedOrder__preloader_2h41y\"\n};"]}