{"remainingRequest":"C:\\Users\\cherv\\OneDrive\\Рабочий стол\\deltaway.20\\node_modules\\babel-loader\\lib\\index.js??ref--5-2!C:\\Users\\cherv\\OneDrive\\Рабочий стол\\deltaway.20\\src\\apps\\admin\\html.js","dependencies":[{"path":"C:\\Users\\cherv\\OneDrive\\Рабочий стол\\deltaway.20\\src\\apps\\admin\\html.js","mtime":1671546430000},{"path":"C:\\Users\\cherv\\OneDrive\\Рабочий стол\\deltaway.20\\.babelrc","mtime":1671546158000},{"path":"C:\\Users\\cherv\\OneDrive\\Рабочий стол\\deltaway.20\\node_modules\\cache-loader\\dist\\cjs.js","mtime":1671546958000},{"path":"C:\\Users\\cherv\\OneDrive\\Рабочий стол\\deltaway.20\\node_modules\\babel-loader\\lib\\index.js","mtime":1671546956000}],"contextDependencies":[],"result":["\"use strict\";\n\nObject.defineProperty(exports, \"__esModule\", {\n    value: true\n});\n\nexports.default = function () {\n    return \"\\n    <!doctype html>\\n    <html lang='ru'>\\n        <head>\\n            <meta charset=\\\"utf-8\\\">\\n            <meta http-equiv='x-ua-compatible' content='ie=edge'>\\n            <meta name='viewport' content='width=device-width, initial-scale=1'>\\n            <title>\\u0410\\u0434\\u043C\\u0438\\u043D \\u043F\\u0430\\u043D\\u0435\\u043B\\u044C</title>\\n            <link rel='stylesheet' type='text/css' href='/public/admin.chunk.css'>\\n            <link rel=\\\"stylesheet\\\" href=\\\"https://fonts.googleapis.com/css?family=Roboto:300,400,500\\\">\\n            <link rel=\\\"stylesheet\\\" href=\\\"https://fonts.googleapis.com/icon?family=Material+Icons\\\">\\n            <link rel='shortcut icon' href='/client/images/favicon.png' type='image/png'>\\n        </head>\\n        <body>\\n            <div id='app'></div>\\n            <script src='/public/vendors-admin.chunk.js' defer='defer'></script>\\n            <script src='/public/admin.chunk.js' defer='defer'></script>\\n        </body>\\n    </html>\";\n};",null]}